LICENSE
README.md
__init__.py
flask_quick_sql.py
flask_quick_sql-1.0.2.dist-info/LICENSE
flask_quick_sql-1.0.2.dist-info/METADATA
flask_quick_sql-1.0.2.dist-info/WHEEL
flask_quick_sql-1.0.2.dist-info/RECORD
