Metadata-Version: 2.1
Name: flask-quick-sql
Version: 1.0.2
Summary: A quick way to run SQL in your Flask app.
Home-page: https://github.com/le717/flask-quick-sql
License: Public domain
Author: Caleb
Author-email: le717@users.noreply.github.com
Requires-Python: >=3.10,<4.0
Classifier: Development Status :: 5 - Production/Stable
Classifier: Environment :: Plugins
Classifier: Framework :: Flask
Classifier: License :: Other/Proprietary License
Classifier: License :: Public Domain
Classifier: Programming Language :: Python
Classifier: Programming Language :: Python :: 3
Classifier: Programming Language :: Python :: 3.10
Classifier: Programming Language :: Python :: 3.11
Classifier: Programming Language :: Python :: 3
Classifier: Programming Language :: Python :: 3.10
Classifier: Programming Language :: Python :: 3.11
Classifier: Topic :: Database
Classifier: Topic :: Software Development :: Libraries
Classifier: Topic :: Software Development :: Libraries :: Python Modules
Classifier: Typing :: Typed
Requires-Dist: flask (>=2.2.3,<3.0.0)
Requires-Dist: flask-sqlalchemy (>=3.0.3,<4.0.0)
Project-URL: Repository, https://github.com/le717/flask-quick-sql
